README.rst
iso_639_codes.py
setup.py
iso_639_codes.egg-info/PKG-INFO
iso_639_codes.egg-info/SOURCES.txt
iso_639_codes.egg-info/dependency_links.txt
iso_639_codes.egg-info/not-zip-safe
iso_639_codes.egg-info/top_level.txt