Metadata-Version: 1.1
Name: iso-639-codes
Version: 0.0.1
Summary: ISO 639-1 ↔ ISO 639-2 code translation.
Home-page: https://github.com/Bystroushaak/iso_639_codes
Author: Bystroushaak
Author-email: bystrousak@kitakitsune.org
License: MIT
Platform: UNKNOWN
Classifier: Development Status :: 4 - Beta
Classifier: Intended Audience :: Developers
Classifier: Programming Language :: Python
Classifier: Programming Language :: Python :: 2
Classifier: Programming Language :: Python :: 2.7
Classifier: License :: OSI Approved :: MIT License
